[
    { "id": 1, "videoUrl": "https://www.youtube.com/embed/ZkbwJ4gVohQ?si=cysi6l28cU6K_Ee5" },
    { "id": 2, "videoUrl": "https://www.youtube.com/embed/z94NB15LIfg?si=Ij0z3bRrapN36d7G" },
    { "id": 3, "videoUrl": "https://www.youtube.com/embed/NGGNdJiCr78?si=DP8SFVNXKnfG_kSc" },
    { "id": 4, "videoUrl": "https://www.youtube.com/embed/wSoQ8B1E0is?si=X_8aqK8bnSUiGQq-" },
    { "id": 5, "videoUrl": "https://www.youtube.com/embed/z30mE3KBhcM?si=TNe_xOc0JjymjBPc" },
    { "id": 6, "videoUrl": "https://www.youtube.com/embed/ZvcqGUXPKrA?si=UZV9DvaTi_VqioA8" },
    { "id": 7, "videoUrl": "https://www.youtube.com/embed/LRVntGZ1zCc?si=Zaa5D4_GmqQohwpe" },
    { "id": 8, "videoUrl": "https://www.youtube.com/embed/OZHYl-JhY1A?si=cGmk9xRBNS70SmaW" },
    { "id": 9, "videoUrl": "https://www.youtube.com/embed/yXES9S0qnlo?si=2INL9LdjzUnbX2Ys" }
  ]
  